simple_result/__init__.py
simple_result/result.py
simple_result-0.2.0.dist-info/licenses/LICENSE.md
simple_result-0.2.0.dist-info/METADATA
simple_result-0.2.0.dist-info/WHEEL
simple_result-0.2.0.dist-info/top_level.txt
simple_result-0.2.0.dist-info/RECORD
