Metadata-Version: 2.4
Name: simple-result
Version: 0.2.0
Summary: A very simple, fully typed Rust-like Result type for Python 3.
Author-email: Dairo Mosquera <dairoandres115@outlook.com>
Project-URL: Homepage, https://github.com/daireto/simple-result
Project-URL: Issues, https://github.com/daireto/simple-result/issues
Project-URL: Repository, https://github.com/daireto/simple-result
Keywords: result,result-pattern,rust-like,python
Classifier: Programming Language :: Python :: 3.10
Classifier: Programming Language :: Python :: 3.11
Classifier: Programming Language :: Python :: 3.12
Classifier: Programming Language :: Python :: 3.13
Classifier: Programming Language :: Python :: 3.14
Classifier: License :: OSI Approved :: MIT License
Classifier: Operating System :: OS Independent
Classifier: Intended Audience :: Developers
Requires-Python: >=3.10
License-File: LICENSE.md
Dynamic: license-file
